easy_gui/__init__.py
easy_gui/master_classes.py
easy_gui/styles.py
easy_gui/util.py
easy_gui/widgets.py
easy_gui/resources/transparent.ico
easy_gui-0.4.10.dist-info/LICENSE.txt
easy_gui-0.4.10.dist-info/METADATA
easy_gui-0.4.10.dist-info/WHEEL
easy_gui-0.4.10.dist-info/top_level.txt
easy_gui-0.4.10.dist-info/RECORD
