Metadata-Version: 2.1
Name: easy-gui
Version: 0.4.10
Summary: Easy Python GUI applications (tkinter wrapper)
Home-page: https://github.com/zachbateman/easy_gui.git
Download-URL: https://github.com/zachbateman/easy_gui/archive/v_0.4.10.tar.gz
Author: Zach Bateman
License: MIT
Keywords: GUI,TKINTER,APPLICATION,SIMPLE,EASY
Classifier: Development Status :: 3 - Alpha
Classifier: License :: OSI Approved :: MIT License
Classifier: Programming Language :: Python :: 3
Classifier: Programming Language :: Python :: 3.7
Classifier: Programming Language :: Python :: 3.8
Classifier: Programming Language :: Python :: 3.9
Classifier: Programming Language :: Python :: 3.10
Classifier: Programming Language :: Python :: 3.11
License-File: LICENSE.txt
Requires-Dist: matplotlib
